msearch/__about__.py
msearch/__init__.py
msearch/browse.py
msearch/main.py
msearch/parse.py
msearch/requirements.txt
msearch/search.py
msearch/test.py
msearch/resources
msearch-1.0.7.dist-info/METADATA
msearch-1.0.7.dist-info/WHEEL
msearch-1.0.7.dist-info/licenses/LICENSE
msearch-1.0.7.dist-info/RECORD
