Metadata-Version: 2.3
Name: msearch
Version: 1.0.7
Summary: Search web, hf, pypi, stackovf
Author: mbodiai
License-Expression: Apache-2.0
License-File: LICENSE
Classifier: Development Status :: 4 - Beta
Classifier: Programming Language :: Python
Classifier: Programming Language :: Python :: 3.10
Classifier: Programming Language :: Python :: 3.11
Classifier: Programming Language :: Python :: 3.12
Classifier: Programming Language :: Python :: Implementation :: CPython
Classifier: Programming Language :: Python :: Implementation :: PyPy
Requires-Python: >=3.10
Requires-Dist: bs4==0.0.2
Requires-Dist: git-python
Requires-Dist: html2text==2024.2.26
Requires-Dist: html5lib>=1.1
Requires-Dist: mbpy
Requires-Dist: minspect
Requires-Dist: mrender
Requires-Dist: prompt-toolkit>=3.0.48
Requires-Dist: pygithub
Requires-Dist: requests==2.32.3
Requires-Dist: rich-click>=1.8.3
Requires-Dist: rich==13.7.1
Requires-Dist: twine>=5.1.1
